monascastatsd/__init__.py
monascastatsd/client.py
monascastatsd/common.py
monascastatsd/connection.py
monascastatsd/counter.py
monascastatsd/gauge.py
monascastatsd/metricbase.py
monascastatsd/timer.py
monasca_statsd-2.7.0.dist-info/AUTHORS
monasca_statsd-2.7.0.dist-info/LICENSE
monasca_statsd-2.7.0.dist-info/METADATA
monasca_statsd-2.7.0.dist-info/WHEEL
monasca_statsd-2.7.0.dist-info/pbr.json
monasca_statsd-2.7.0.dist-info/top_level.txt
monasca_statsd-2.7.0.dist-info/RECORD
