Metadata-Version: 2.1
Name: monasca-statsd
Version: 2.7.0
Summary: Monasca statsd Python client
Home-page: https://opendev.org/openstack/monasca-statsd
Maintainer: monasca
Maintainer-email: monasca@lists.launchpad.net
License: Apache-2
Keywords: openstack,monitoring,statsd
Platform: UNKNOWN
Classifier: Development Status :: 5 - Production/Stable
Classifier: License :: OSI Approved :: Apache Software License
Classifier: Topic :: System :: Monitoring
Classifier: Programming Language :: Python
Classifier: Programming Language :: Python :: Implementation :: CPython
Classifier: Programming Language :: Python :: 3 :: Only
Classifier: Programming Language :: Python :: 3
Classifier: Programming Language :: Python :: 3.6
Classifier: Programming Language :: Python :: 3.7
Classifier: Programming Language :: Python :: 3.8
Requires-Python: >=3.6
Requires-Dist: six (>=1.12.0)
